explainable_ai_tf/__init__.py
explainable_ai_tf/activation_per_layer.py
explainable_ai_tf/common.py
explainable_ai_tf/evaluation_metrics.py
explainable_ai_tf/explainability_check.py
explainable_ai_tf/explainability_heatmaps.py
explainable_ai_tf/explanation_wrapper.py
explainable_ai_tf/grad_cam.py
explainable_ai_tf/guided_backpropagation.py
explainable_ai_tf/tf_xai_methods_api.py
explainable_ai_tf/visualization_patterns_check.py
explainable_ai_tf/fusion_grad/__init__.py
explainable_ai_tf/fusion_grad/fusion_grad.py
explainable_ai_tf/fusion_grad/fusion_grad_core.py
explainable_ai_tf/smooth_grad/__init__.py
explainable_ai_tf/smooth_grad/smooth_grad.py
explainable_ai_tf/smooth_grad/smooth_grad_core.py
explainable_ai_tf-0.1.2.dist-info/METADATA
explainable_ai_tf-0.1.2.dist-info/WHEEL
explainable_ai_tf-0.1.2.dist-info/top_level.txt
explainable_ai_tf-0.1.2.dist-info/RECORD
